maxsmart/__init__.py
maxsmart/const.py
maxsmart/discovery.py
maxsmart/exceptions.py
maxsmart/messages.py
maxsmart/utils.py
maxsmart/device/__init__.py
maxsmart/device/commands.py
maxsmart/device/configuration.py
maxsmart/device/control.py
maxsmart/device/core.py
maxsmart/device/hardware.py
maxsmart/device/polling.py
maxsmart/device/statistics.py
maxsmart/device/time.py
maxsmart-2.1.0.dist-info/licenses/LICENSE
maxsmart-2.1.0.dist-info/METADATA
maxsmart-2.1.0.dist-info/WHEEL
maxsmart-2.1.0.dist-info/top_level.txt
maxsmart-2.1.0.dist-info/RECORD
