Metadata-Version: 2.4
Name: maxsmart
Version: 2.1.0
Summary: A comprehensive Python library for controlling Revogi-based Max Hauri MaxSmart PowerStrips and Smart Plugs
Author-email: Superkikim <your-email@example.com>
Maintainer-email: Superkikim <your-email@example.com>
License: MIT
Project-URL: Homepage, https://github.com/superkikim/maxsmart
Project-URL: Documentation, https://github.com/superkikim/maxsmart/blob/main/README.md
Project-URL: Repository, https://github.com/superkikim/maxsmart.git
Project-URL: Bug Tracker, https://github.com/superkikim/maxsmart/issues
Project-URL: Changelog, https://github.com/superkikim/maxsmart/blob/main/CHANGELOG.md
Keywords: maxsmart,revogi,smart,plug,power,strip,home,automation,iot
Classifier: Development Status :: 5 - Production/Stable
Classifier: Intended Audience :: Developers
Classifier: Intended Audience :: End Users/Desktop
Classifier: Intended Audience :: System Administrators
Classifier: License :: OSI Approved :: MIT License
Classifier: Operating System :: OS Independent
Classifier: Programming Language :: Python :: 3
Classifier: Programming Language :: Python :: 3.7
Classifier: Programming Language :: Python :: 3.8
Classifier: Programming Language :: Python :: 3.9
Classifier: Programming Language :: Python :: 3.10
Classifier: Programming Language :: Python :: 3.11
Classifier: Programming Language :: Python :: 3.12
Classifier: Topic :: Home Automation
Classifier: Topic :: System :: Networking
Classifier: Topic :: Software Development :: Libraries :: Python Modules
Requires-Python: >=3.7
License-File: LICENSE
Requires-Dist: aiohttp>=3.8.0
Requires-Dist: getmac>=0.9.5
Provides-Extra: dev
Requires-Dist: pytest>=7.0; extra == "dev"
Requires-Dist: pytest-asyncio>=0.21.0; extra == "dev"
Requires-Dist: black>=22.0; extra == "dev"
Requires-Dist: isort>=5.0; extra == "dev"
Requires-Dist: flake8>=4.0; extra == "dev"
Requires-Dist: mypy>=0.991; extra == "dev"
Provides-Extra: examples
Requires-Dist: matplotlib>=3.5.0; extra == "examples"
Dynamic: license-file
